tdbase/__init__.py
tdbase/__main__.py
tdbase/lineinfo.py
tdbase/nodes.py
tdbase/parser.py
tdbase/py.typed
tdbase-0.0.5.dist-info/LICENSE
tdbase-0.0.5.dist-info/METADATA
tdbase-0.0.5.dist-info/WHEEL
tdbase-0.0.5.dist-info/top_level.txt
tdbase-0.0.5.dist-info/RECORD
