Metadata-Version: 2.1
Name: tdbase
Version: 0.0.5
Summary: Text based database package
Home-page: UNKNOWN
Author: Jesper Ribbe
License: UNKNOWN
Platform: UNKNOWN
Classifier: Programming Language :: Python :: 3
Classifier: License :: OSI Approved :: MIT License
Classifier: Operating System :: OS Independent
Requires-Python: >=3.6
